LICENSE
README.rst
setup.py
plastics/__init__.py
plastics.egg-info/PKG-INFO
plastics.egg-info/SOURCES.txt
plastics.egg-info/dependency_links.txt
plastics.egg-info/requires.txt
plastics.egg-info/top_level.txt
plastics/strap/__init__.py
plastics/strap/dissolution_steps.py
plastics/strap/precipitation_steps.py
plastics/strap/process_model.py
plastics/strap/process_settings.py
plastics/strap/property_package.py
plastics/strap/simulation.py
plastics/strap/systems.py
plastics/strap/tea.py
plastics/strap/units.py