Metadata-Version: 2.1
Name: plastics
Version: 0.1.2
Summary: Plastic processing models in BioSTEAM
Home-page: https://github.com/yoelcortes/plastics
Download-URL: https://github.com/yoelcortes/plastics
Author: Yoel Cortes-Pena
Author-email: yoelcortes@gmail.com
License: MIT
Keywords: chemical process simulation plastic bioprocess engineering STRAP solvent targeted dissolution precipitation
Platform: Windows
Platform: Mac
Platform: Linux
Classifier: Development Status :: 3 - Alpha
Classifier: Environment :: Console
Classifier: License :: OSI Approved :: MIT License
Classifier: Programming Language :: Python :: 3.6
Classifier: Programming Language :: Python :: 3.7
Classifier: Topic :: Scientific/Engineering
Classifier: Topic :: Scientific/Engineering :: Chemistry
Classifier: Topic :: Scientific/Engineering :: Mathematics
Requires-Python: >=3.9
License-File: LICENSE
